systemID_light/__init__.py
systemID_light/core/__init__.py
systemID_light/core/algorithms/__init__.py
systemID_light/core/algorithms/eigensystem_realization_algorithm.py
systemID_light/core/algorithms/eigensystem_realization_algorithm_from_initial_condition_response.py
systemID_light/core/algorithms/eigensystem_realization_algorithm_with_data_correlation.py
systemID_light/core/algorithms/eigensystem_realization_algorithm_with_data_correlation_from_initial_condition_response.py
systemID_light/core/algorithms/markov_controller_parameters_from_observer_controller_markov_parameters.py
systemID_light/core/algorithms/markov_parameters_from_observer_markov_parameters.py
systemID_light/core/algorithms/observer_controller_eigensystem_realization_algorithm.py
systemID_light/core/algorithms/observer_controller_identification_algorithm.py
systemID_light/core/algorithms/observer_gain_markov_parameters_from_observer_markov_parameters.py
systemID_light/core/algorithms/observer_kalman_identification_algorithm.py
systemID_light/core/algorithms/observer_kalman_identification_algorithm_with_observer.py
systemID_light/core/algorithms/time_varying_eigensystem_realization_algorithm.py
systemID_light/core/algorithms/time_varying_eigensystem_realization_algorithm_from_initial_condition_response.py
systemID_light/core/algorithms/time_varying_markov_parameters_from_time_varying_observer_markov_parameters.py
systemID_light/core/algorithms/time_varying_observer_gain_markov_parameters_from_time_varying_observer_markov_parameters.py
systemID_light/core/algorithms/time_varying_observer_kalman_identification_algorithm_with_observer.py
systemID_light/core/functions/__init__.py
systemID_light/core/functions/augment_data.py
systemID_light/core/functions/continuous_to_discrete.py
systemID_light/core/functions/interpolate.py
systemID_light/core/functions/mac_and_msv.py
systemID_light/core/functions/observability_matrix.py
systemID_light/core/functions/polynomial_basis_functions.py
systemID_light-25.5.dist-info/METADATA
systemID_light-25.5.dist-info/WHEEL
systemID_light-25.5.dist-info/top_level.txt
systemID_light-25.5.dist-info/RECORD
